README.md
manage.py
setup.cfg
setup.py
CarpalRouting.egg-info/PKG-INFO
CarpalRouting.egg-info/SOURCES.txt
CarpalRouting.egg-info/dependency_links.txt
CarpalRouting.egg-info/entry_points.txt
CarpalRouting.egg-info/requires.txt
CarpalRouting.egg-info/top_level.txt
carpalrouting/__init__.py
carpalrouting/geofence.py
carpalrouting/grouping.py
carpalrouting/models.py
carpalrouting/optimize.py
carpalrouting/optimize_alpha.py
carpalrouting/optimize_wave.py
tests/__init__.py
tests/data.py
tests/test_driver_location_grouping.py
tests/test_optimizer.py