Metadata-Version: 1.0
Name: CarpalRouting
Version: 0.0.0.53
Summary: A routing optimization engine.
Home-page: UNKNOWN
Author: CarPal Fleet
Author-email: nick@carpal.me
License: Apache License 2.0
Keywords: routing optimization,last mile
Platform: any
